<?xml version="1.0" encoding="UTF-8" standalone="yes"?>
<w:document mc:Ignorable="w14 wp14" xmlns:m="http://schemas.openxmlformats.org/officeDocument/2006/math" xmlns:mc="http://schemas.openxmlformats.org/markup-compatibility/2006" xmlns:o="urn:schemas-microsoft-com:office:office" xmlns:r="http://schemas.openxmlformats.org/officeDocument/2006/relationships" xmlns:v="urn:schemas-microsoft-com:vml" xmlns:w="http://schemas.openxmlformats.org/wordprocessingml/2006/main" xmlns:w10="urn:schemas-microsoft-com:office:word" xmlns:w14="http://schemas.microsoft.com/office/word/2010/wordml" xmlns:wne="http://schemas.microsoft.com/office/word/2006/wordml" xmlns:wp="http://schemas.openxmlformats.org/drawingml/2006/wordprocessingDrawing" xmlns:wp14="http://schemas.microsoft.com/office/word/2010/wordprocessingDrawing" xmlns:wpc="http://schemas.microsoft.com/office/word/2010/wordprocessingCanvas" xmlns:wpg="http://schemas.microsoft.com/office/word/2010/wordprocessingGroup" xmlns:wpi="http://schemas.microsoft.com/office/word/2010/wordprocessingInk" xmlns:wps="http://schemas.microsoft.com/office/word/2010/wordprocessingShape">
	<w:body>
		<w:p w:rsidP="00EA68DC" w:rsidR="001A6335" w:rsidRDefault="00EA68DC">
			<w:bookmarkStart w:id="0" w:name="_GoBack"/>
			<w:bookmarkEnd w:id="0"/>
			<w:r w:rsidRPr="00C703AC">
				<w:t>DOCX.js is a free open source library for generating Microsoft Word Documents using pure client-side JavaScript.</w:t>
			</w:r>
		</w:p>
		<w:p w:rsidP="00EA68DC" w:rsidR="001A6335" w:rsidRDefault="00EA68DC">
			<w:r w:rsidRPr="00C703AC">
				<w:t>It was developed by James Hall at Snapshot Media.</w:t>
			</w:r>
		</w:p>
		<w:sectPr w:rsidR="001A6335" w:rsidSect="0067748C">
			<w:headerReference r:id="rId7" w:type="even"/>
			<w:headerReference r:id="rId8" w:type="default"/>
			<w:footerReference r:id="rId9" w:type="even"/>
			<w:footerReference r:id="rId10" w:type="default"/>
			<w:headerReference r:id="rId11" w:type="first"/>
			<w:footerReference r:id="rId12" w:type="first"/>
			<w:pgSz w:code="9" w:h="16839" w:w="11907"/>
			<w:pgMar w:bottom="1134" w:footer="720" w:gutter="0" w:header="720" w:left="1417" w:right="1417" w:top="1417"/>
			<w:cols w:space="720"/>
			<w:docGrid w:linePitch="360"/>
		</w:sectPr>
	</w:body>
</w:document>
